{
  "adlist3": [
    {
    "channel": "",
    "extInfo": {
      "position": "102002",
      "packageType": "1",
      "showPosition": "0",
      "show_limit": "0",
      "loginStatus": "0",
      "cashDays": "0",
      "tag": "0",
      "deviceModel": "",
      "data": "0",
      "chapterLength": "0",
      "monthDays": "0",
      "book_auth": "0",
      "priority": "0",
      "ref_info": "",
      "black": "0",
      "dayHigh": "0",
      "live_time": "0",
      "publishTime": "2018-10-24 00:00:00",
      "property": "-1",
      "actionType": "0",
      "category": "0",
      "closeTime": "2018-10-31 00:00:00",
      "bookNews": "0",
      "red": "1",
      "channelStatus": "0",
      "dayLow": "0",
      "forceLogin": "0",
      "month": "0",
      "cash": "0",
      "userNew": "0"
    },
    "id": 70317699,
    "imageUrl": "https:\/\/16dd-advertise-1252317822.file.myqcloud.com\/ad\/3862_2018-10-22\/1540202520771_465791.jpg",
    "intro": "",
    "title": "讲讲我的恐怖经历",
    "type": 2,
    "value": "tpdata.html?lid=342932",
    "valueType": 0
  },
    {
    "channel": "",
    "extInfo": {
      "position": "102002",
      "packageType": "1",
      "showPosition": "0",
      "show_limit": "0",
      "loginStatus": "0",
      "cashDays": "0",
      "tag": "0",
      "deviceModel": "",
      "data": "0",
      "chapterLength": "0",
      "monthDays": "0",
      "book_auth": "0",
      "priority": "0",
      "ref_info": "",
      "black": "0",
      "dayHigh": "0",
      "live_time": "0",
      "publishTime": "2018-09-28 09:35:15",
      "property": "1",
      "actionType": "0",
      "category": "0",
      "closeTime": "2018-10-31 00:00:00",
      "bookNews": "0",
      "red": "1",
      "channelStatus": "0",
      "dayLow": "0",
      "forceLogin": "0",
      "month": "0",
      "cash": "0",
      "userNew": "0"
    },
    "id": 70310333,
    "imageUrl": "http:\/\/wfqqreader.3g.qq.com\/cover\/topic\/119201207_70003369_1508211325498.jpg",
    "intro": "",
    "title": "目之所及，皆是经验",
    "type": 2,
    "value": "tpdata.html?lid=332523",
    "valueType": 0
  },
    {
    "channel": "",
    "extInfo": {
      "position": "102002",
      "packageType": "1",
      "showPosition": "0",
      "show_limit": "0",
      "loginStatus": "0",
      "cashDays": "0",
      "tag": "0",
      "deviceModel": "",
      "data": "0",
      "chapterLength": "0",
      "monthDays": "0",
      "book_auth": "0",
      "priority": "0",
      "ref_info": "",
      "black": "0",
      "dayHigh": "0",
      "live_time": "0",
      "publishTime": "2018-07-21 12:30:14",
      "property": "-1",
      "actionType": "0",
      "category": "0",
      "closeTime": "2019-03-28 00:00:00",
      "bookNews": "0",
      "red": "1",
      "channelStatus": "0",
      "dayLow": "0",
      "forceLogin": "0",
      "month": "0",
      "cash": "0",
      "userNew": "0"
    },
    "id": 70288158,
    "imageUrl": "http:\/\/wfqqreader.3g.qq.com\/cover\/topic\/119201207_0_1515564995560.jpg",
    "intro": "我的老板是神仙，你敢信？",
    "title": "和神仙的不平等条约",
    "type": 2,
    "value": "tpdata.html?lid=335222",
    "valueType": 0
  },
    {
    "channel": "",
    "extInfo": {
      "position": "102002",
      "packageType": "1",
      "showPosition": "0",
      "show_limit": "0",
      "loginStatus": "0",
      "cashDays": "0",
      "tag": "0",
      "deviceModel": "",
      "data": "0",
      "chapterLength": "0",
      "monthDays": "0",
      "book_auth": "0",
      "priority": "0",
      "ref_info": "",
      "black": "0",
      "dayHigh": "0",
      "live_time": "0",
      "publishTime": "2018-06-08 15:16:56",
      "property": "-1",
      "actionType": "0",
      "category": "0",
      "closeTime": "2019-06-30 00:00:00",
      "bookNews": "0",
      "red": "1",
      "channelStatus": "0",
      "dayLow": "0",
      "forceLogin": "0",
      "month": "0",
      "cash": "0",
      "userNew": "0"
    },
    "id": 70274486,
    "imageUrl": "http:\/\/wfqqreader.3g.qq.com\/cover\/topic\/119201207_0_1528442278252.jpg",
    "intro": "",
    "title": "识于微时，青梅竹马",
    "type": 2,
    "value": "tpdata.html?lid=339388",
    "valueType": 0
  }],
  "finList": [
    {
    "lpushname": "冷宫公主化身兽性腹黑大姐大，凤凌天下！",
    "cpushname": "魅王火妃:兽血黑道大姐大",
    "finished": "1",
    "type": "0",
    "intro": "现代大姐大穿越成为备受欺凌的冷宫小公主，真是老天不开眼！\r\n  有本宫在此，看谁还敢放肆！皇孙贵族、世家少爷休",
    "id": "446050",
    "cat3Info": "30000:小说:小说,30001:玄幻言情:幻情,30002:东方玄幻:玄幻",
    "author": "月鎏香",
    "title": "魅王火妃：兽黑大姐大",
    "cover": "http:\/\/wfqqreader-1252317822.image.myqcloud.com\/cover\/50\/446050\/b_446050.jpg",
    "categoryInfoV4Slave": "",
    "catName": "幻情",
    "totalWords": "2795682",
    "pushName": "魅王火妃:兽血黑道大姐大",
    "categoryInfoV4": "30000:小说:小说,30001:玄幻言情:幻情,30002:东方玄幻:玄幻"
  },
    {
    "lpushname": "重生前，她如草芥任人宰割，欺之压之，最后惨死于闺蜜之手。",
    "cpushname": "豪门重生：总裁大人，放肆宠",
    "finished": "1",
    "type": "0",
    "intro": "“宝贝，乖，来，张嘴含住...”某男紧盯着娇羞的女人邪魅道。“不要，唔...好苦。”牧若安只是轻微感冒，就被男",
    "id": "20528989",
    "cat3Info": "30000:小说:小说,30020:现代言情:现言,30028:豪门世家:豪门",
    "author": "云梦悠悠",
    "title": "豪门重生：总裁大人，放肆宠",
    "cover": "20528989",
    "categoryInfoV4Slave": "",
    "catName": "现言",
    "totalWords": "2106723",
    "pushName": "豪门重生：总裁大人，放肆宠",
    "categoryInfoV4": "30000:小说:小说,30020:现代言情:现言,30028:豪门世家:豪门"
  },
    {
    "lpushname": "叮！\r\n“系统提示，前方有一大波红包雨逼近，请宿主做好准备抢红包！”\r\n“哇！竟然抢到了神级武脉！”\r\n“哇！",
    "cpushname": "无敌红包皇帝",
    "finished": "1",
    "type": "0",
    "intro": "叮！\r\n“系统提示，前方有一大波红包雨逼近，请宿主做好准备抢红包！”\r\n“哇！竟然抢到了神级武脉！”\r\n“哇！",
    "id": "22173193",
    "cat3Info": "20000:小说:小说,20001:玄幻:玄幻,20002:东方玄幻:东方玄幻",
    "author": "晨锅锅",
    "title": "无敌红包皇帝",
    "cover": "22173193",
    "categoryInfoV4Slave": "",
    "catName": "玄幻",
    "totalWords": "921091",
    "pushName": "无敌红包皇帝",
    "categoryInfoV4": "20000:小说:小说,20001:玄幻:玄幻,20002:东方玄幻:东方玄幻"
  },
    {
    "lpushname": "兵王重生获得装逼系统，仇人通通碾压！美女全部来怀。不服你也装逼啊？",
    "cpushname": "都市最强装逼系统",
    "finished": "1",
    "type": "0",
    "intro": "【最火爆新书】叶秋重生获得装逼系统，当最萌萝莉的奶爸，教美女大明星唱歌，做宗师级美食大餐，写最畅销的小说……屹",
    "id": "14589102",
    "cat3Info": "20000:小说:小说,20019:都市:都市,20026:异术超能:异能",
    "author": "必火",
    "title": "都市最强装逼系统",
    "cover": "14589102",
    "categoryInfoV4Slave": "",
    "catName": "都市",
    "totalWords": "4130471",
    "pushName": "都市最强装逼系统",
    "categoryInfoV4": "20000:小说:小说,20019:都市:都市,20026:异术超能:异能"
  },
    {
    "lpushname": "累计销售量达千万册的青春幻想小说，被誉为“东方的《哈利·波特》”，作者江南本人获得2013年中国作家富豪榜榜首",
    "cpushname": "龙族（1-4合集）",
    "finished": "1",
    "type": "0",
    "intro": "累计销售量达千万册的青春幻想小说，被誉为“东方的《哈利·波特》”，作者江南本人获得2013年中国作家富豪榜榜首",
    "id": "933334",
    "cat3Info": ",,14306::",
    "author": "江南",
    "title": "龙族（1-4合集）",
    "cover": "933334",
    "categoryInfoV4Slave": "10000:出版:出版,14300:青春文学:青春,14307:大陆原创:大陆原创",
    "catName": "青春",
    "totalWords": "2091633",
    "pushName": "龙族（1-4合集）",
    "categoryInfoV4": "10000:出版:出版,14300:青春文学:青春,14306:玄幻\/新武侠\/魔幻\/科幻:幻侠"
  },
    {
    "lpushname": "近十年最畅销的历史书，带你走进明朝三百年。",
    "cpushname": "明朝那些事儿（全集）",
    "finished": "1",
    "type": "0",
    "intro": "《明朝那些事儿》主要讲述的是从1344年到1644年这三百年间关于明朝的一些故事。以史料为基础，以年代和具体人",
    "id": "822995",
    "cat3Info": ",,14408::",
    "author": "当年明月",
    "title": "明朝那些事儿（全集）",
    "cover": "822995",
    "categoryInfoV4Slave": "",
    "catName": "历史",
    "totalWords": "1472549",
    "pushName": "明朝那些事儿（全集）",
    "categoryInfoV4": "10000:出版:出版,14400:历史:历史,14408:历史普及读物:普及读物"
  }],
  "freeLimit": [
    {
    "lpushname": "",
    "cpushname": "恋爱放映式",
    "finished": "1",
    "type": "0",
    "intro": "特立独行的影视总裁沈天成，撞上吐槽影会的影评行家柳笛心。他惊讶于她的独到眼光和犀利点评，她折服于他的行事严谨和",
    "id": "23061423",
    "cat3Info": ",,14302::",
    "author": "陌顷寒",
    "title": "恋爱放映式",
    "cover": "23061423",
    "categoryInfoV4Slave": "10000:出版:出版,14300:青春文学:青春,14307:大陆原创:大陆原创",
    "catName": "青春",
    "totalWords": "129763",
    "pushName": "恋爱放映式",
    "categoryInfoV4": "10000:出版:出版,14300:青春文学:青春,14302:爱情\/情感:情感"
  },
    {
    "lpushname": "大学毕业生惨被女友抛弃，却获得修仙传承，从此一路高歌猛进，走向最巅峰！",
    "cpushname": "修仙传承:乡村妙手小仙医",
    "finished": "0",
    "type": "0",
    "intro": "大学毕业生惨被女友抛弃，却意外获得无上修仙传承，从此一路高歌猛进，走向人生最巅峰！你有心脏病？没事，我这有一枚",
    "id": "906895",
    "cat3Info": "20000:小说:小说,20019:都市:都市,20020:都市生活:生活",
    "author": "风烟望五津",
    "title": "乡村妙手小仙医",
    "cover": "906895",
    "categoryInfoV4Slave": "",
    "catName": "都市",
    "totalWords": "4001311",
    "pushName": "修仙传承:乡村妙手小仙医",
    "categoryInfoV4": "20000:小说:小说,20019:都市:都市,20020:都市生活:生活"
  },
    {
    "lpushname": "她闪婚一位没钱，没房，没车的他，不想他摇身一变却成了顶级钻石王老五……",
    "cpushname": "蜜婚：老公大人轻点撩",
    "finished": "1",
    "type": "0",
    "intro": "陆七，京都陆家千金，结婚当天被未婚夫抛弃，新娘成了她同父异母的妹妹。\r\n母亲气得气血攻心，被送进医院抢救。\r\n",
    "id": "14991887",
    "cat3Info": "30000:小说:小说,30020:现代言情:现言,30028:豪门世家:豪门",
    "author": "清音随琴",
    "title": "蜜婚：老公大人轻点撩",
    "cover": "14991887",
    "categoryInfoV4Slave": "",
    "catName": "现言",
    "totalWords": "2443532",
    "pushName": "蜜婚：老公大人轻点撩",
    "categoryInfoV4": "30000:小说:小说,30020:现代言情:现言,30028:豪门世家:豪门"
  },
    {
    "lpushname": "",
    "cpushname": "抢神仙红包:竟获七十九变",
    "finished": "1",
    "type": "0",
    "intro": "乡村菜农张枫，一次无意间溜达却发现女神洗澡，接而脑袋发重跌落荷塘。被女神救起后，发现手机微信更新，从此接触各路",
    "id": "908378",
    "cat3Info": "20000:小说:小说,20019:都市:都市,20026:异术超能:异能",
    "author": "平山子",
    "title": "抢个红包去种田",
    "cover": "908378",
    "categoryInfoV4Slave": "",
    "catName": "都市",
    "totalWords": "2086850",
    "pushName": "抢神仙红包:竟获七十九变",
    "categoryInfoV4": "20000:小说:小说,20019:都市:都市,20026:异术超能:异能"
  }],
  "fmaleLoves": [
    {
    "lpushname": "开学前一晚睡了个男人，居然是自己的专业讲师！\r\n蓝蔚蔚望着讲台上的人间绝色简直想自戳双眼！\r\n然而，作为自己的",
    "cpushname": "盛宠萌妻：教授老公是总裁",
    "finished": "1",
    "type": "0",
    "intro": "开学前一晚睡了个男人，居然是自己的专业讲师！\r\n蓝蔚蔚望着讲台上的人间绝色简直想自戳双眼！\r\n然而，作为自己的",
    "id": "14987719",
    "cat3Info": "30000:小说:小说,30050:游戏竞技:游戏,30052:网游情缘:网游",
    "author": "蓝蔚蔚",
    "title": "盛宠萌妻：教授老公是总裁",
    "cover": "http:\/\/wfqqreader-1252317822.image.myqcloud.com\/cover\/719\/14987719\/b_14987719.jpg",
    "categoryInfoV4Slave": "",
    "catName": "游戏",
    "totalWords": "1804017",
    "pushName": "盛宠萌妻：教授老公是总裁",
    "categoryInfoV4": "30000:小说:小说,30050:游戏竞技:游戏,30052:网游情缘:网游"
  },
    {
    "lpushname": "傲娇小公主，一夜魂穿成19岁的陆氏集团总裁夫人。总裁：来，我教你做做运动！",
    "cpushname": "甜心好V5：BOSS宠之过急",
    "finished": "1",
    "type": "0",
    "intro": "【爆笑1V1】“舅舅！老公是什么？为什么他们说你帅得合不拢腿？”\r\n\r\n景伊人，文武双全德才兼备的14岁傲娇小",
    "id": "11437552",
    "cat3Info": "30000:小说:小说,30020:现代言情:现言,30028:豪门世家:豪门",
    "author": "花二宝",
    "title": "甜心V5：BOSS宠之过急",
    "cover": "11437552",
    "categoryInfoV4Slave": "",
    "catName": "现言",
    "totalWords": "1538633",
    "pushName": "甜心好V5：BOSS宠之过急",
    "categoryInfoV4": "30000:小说:小说,30020:现代言情:现言,30028:豪门世家:豪门"
  },
    {
    "lpushname": "重生有军少，虐渣爽翻天。",
    "cpushname": "重生军营：军少，别乱来",
    "finished": "0",
    "type": "0",
    "intro": "身为军人我忠于祖国，身为男人我忠于爱情。\r\n重生后的叶简不需要爱情！不需要亲人！不需要亲情！而是站在众山之巅，",
    "id": "11654007",
    "cat3Info": "30000:小说:小说,30020:现代言情:现言,30028:豪门世家:豪门",
    "author": "直上青云",
    "title": "重生军营之王牌军婚",
    "cover": "11654007",
    "categoryInfoV4Slave": "",
    "catName": "现言",
    "totalWords": "5253502",
    "pushName": "重生军营：军少，别乱来",
    "categoryInfoV4": "30000:小说:小说,30020:现代言情:现言,30028:豪门世家:豪门"
  },
    {
    "lpushname": "想她顾倾之，怎么就找了个二婚夫君，还带着一个六岁孩童，莫不是眼神有问题？",
    "cpushname": "一品娇宠：丞相大人求休妻",
    "finished": "1",
    "type": "0",
    "intro": "想她顾倾之，年方十八，貌美如花，家世显赫，钱随便花。怎么就找了一个二婚夫君，还带着一个六岁孩童，这不是眼神有问",
    "id": "913285",
    "cat3Info": "30000:小说:小说,30013:古代言情:古言,30017:穿越奇情:穿越",
    "author": "半枝红杏",
    "title": "一品娇宠，丞相大人求休妻",
    "cover": "913285",
    "categoryInfoV4Slave": "",
    "catName": "古言",
    "totalWords": "1017042",
    "pushName": "一品娇宠：丞相大人求休妻",
    "categoryInfoV4": "30000:小说:小说,30013:古代言情:古言,30017:穿越奇情:穿越"
  },
    {
    "lpushname": "拓跋猎第一次见到他的小姑娘时，想法是这个粉团子哭得有点像幼狼，让人忍不住！\r\n而百里芸第一次见到她家少将军时，",
    "cpushname": "狼王的娇宠",
    "finished": "0",
    "type": "0",
    "intro": "拓跋猎第一次见到他的小姑娘时，想法是这个粉团子哭得有点像幼狼，让人忍不住！\r\n而百里芸第一次见到她家少将军时，",
    "id": "20938693",
    "cat3Info": "30000:小说:小说,30013:古代言情:古言,30015:古典架空:架空",
    "author": "第一场雪",
    "title": "狼王的娇宠",
    "cover": "20938693",
    "categoryInfoV4Slave": "",
    "catName": "古言",
    "totalWords": "538926",
    "pushName": "狼王的娇宠",
    "categoryInfoV4": "30000:小说:小说,30013:古代言情:古言,30015:古典架空:架空"
  }],
  "goodNew": [
    {
    "lpushname": "他是外科医生中最冷酷的刀客，锋芒毕露。他曾声名狼藉，被封印在血色过往中，以为此生已然万劫不复。风波再起，他在命",
    "cpushname": "风再起时",
    "finished": "1",
    "type": "0",
    "intro": "他是外科医生中最冷酷的刀客，锋芒毕露。他曾声名狼藉，被封印在血色过往中，以为此生已然万劫不复。风波再起，他在命",
    "id": "23364834",
    "cat3Info": ",,14307::",
    "author": "穿行四季",
    "title": "风再起时",
    "cover": "http:\/\/wfqqreader-1252317822.image.myqcloud.com\/cover\/834\/23364834\/b_23364834.jpg",
    "categoryInfoV4Slave": "10000:出版:出版,14300:青春文学:青春,14302:爱情\/情感:情感",
    "catName": "青春",
    "totalWords": "194486",
    "pushName": "风再起时",
    "categoryInfoV4": "10000:出版:出版,14300:青春文学:青春,14307:大陆原创:大陆原创"
  },
    {
    "lpushname": "穿越了，成为了一个没爹没娘的小可怜。\r\n荔枝表示，还好还好，我都习惯了。\r\n  既然这样的话，她就带着一串儿包",
    "cpushname": "农女娇艳：将军，太生猛",
    "finished": "0",
    "type": "0",
    "intro": "穿越了，成为了一个没爹没娘的小可怜。\r\n荔枝表示，还好还好，我都习惯了。\r\n  既然这样的话，她就带着一串儿包",
    "id": "22392020",
    "cat3Info": "30000:小说:小说,30013:古代言情:古言,30017:穿越奇情:穿越",
    "author": "桃花粥粥粥",
    "title": "农女娇艳：将军，太生猛",
    "cover": "22392020",
    "categoryInfoV4Slave": "",
    "catName": "古言",
    "totalWords": "313306",
    "pushName": "农女娇艳：将军，太生猛",
    "categoryInfoV4": "30000:小说:小说,30013:古代言情:古言,30017:穿越奇情:穿越"
  },
    {
    "lpushname": "“丫头，过来。”男人穿着宽松的睡袍，懒懒靠在沙发上，一张俊脸禁欲高冷。\r\n“厉……厉总……”想起两人昨晚在客厅",
    "cpushname": "重生甜妻：总裁老公，你好坏",
    "finished": "0",
    "type": "0",
    "intro": "“丫头，过来。”男人穿着宽松的睡袍，懒懒靠在沙发上，一张俊脸禁欲高冷。\r\n“厉……厉总……”想起两人昨晚在客厅",
    "id": "21801642",
    "cat3Info": "30000:小说:小说,30020:现代言情:现言,30028:豪门世家:豪门",
    "author": "秦爆爆",
    "title": "重生甜妻：总裁老公，你好坏",
    "cover": "21801642",
    "categoryInfoV4Slave": "",
    "catName": "现言",
    "totalWords": "286578",
    "pushName": "重生甜妻：总裁老公，你好坏",
    "categoryInfoV4": "30000:小说:小说,30020:现代言情:现言,30028:豪门世家:豪门"
  },
    {
    "lpushname": "《纵然缘浅，奈何情深》姊妹篇！影视剧已筹拍！他是面容光朗清晖、救死扶伤的白衣天使，也是风评巨差的神秘诱惑者。她",
    "cpushname": "知我如你，情深不负",
    "finished": "1",
    "type": "0",
    "intro": "《纵然缘浅，奈何情深》姊妹篇！影视剧已筹拍！他是面容光朗清晖、救死扶伤的白衣天使，也是风评巨差的神秘诱惑者。她",
    "id": "23360445",
    "cat3Info": ",,14302::",
    "author": "叶落无心",
    "title": "知我如你，情深不负",
    "cover": "23360445",
    "categoryInfoV4Slave": "10000:出版:出版,14300:青春文学:青春,14307:大陆原创:大陆原创",
    "catName": "青春",
    "totalWords": "259920",
    "pushName": "知我如你，情深不负",
    "categoryInfoV4": "10000:出版:出版,14300:青春文学:青春,14302:爱情\/情感:情感"
  }],
  "maleLoves": [
    {
    "lpushname": "楚阳异世重生十六年，原本资质平平，忆起前世记忆，觉醒命运双生子武魂：一阴一阳，一正一反，天才和傻子，诸神与万魔",
    "cpushname": "tencent",
    "finished": "1",
    "type": "0",
    "intro": "楚阳异世重生十六年，原本资质平平，忆起前世记忆，觉醒命运双生子武魂：一阴一阳，一正一反，天才和傻子，诸神与万魔",
    "id": "918567",
    "cat3Info": "20000:小说:小说,20001:玄幻:玄幻,20002:东方玄幻:东方玄幻",
    "author": "弧度",
    "title": "绝世武神",
    "cover": "http:\/\/wfqqreader-1252317822.image.myqcloud.com\/cover\/567\/918567\/b_918567.jpg",
    "categoryInfoV4Slave": "",
    "catName": "玄幻",
    "totalWords": "3101542",
    "pushName": "tencent",
    "categoryInfoV4": "20000:小说:小说,20001:玄幻:玄幻,20002:东方玄幻:东方玄幻"
  },
    {
    "lpushname": "意外获得系统，重回高中时代。诺贝尔奖得住，中科院院士，都是我。",
    "cpushname": "学阀:我的绝美校花未婚妻",
    "finished": "0",
    "type": "0",
    "intro": "意外获得系统，主角段云重回八年前的高中时代。超级五好生系统，德智体美劳全面发展！他是世界上最年轻的诺贝尔奖获得",
    "id": "860655",
    "cat3Info": "20000:小说:小说,20019:都市:都市,20026:异术超能:异能",
    "author": "土豆炖唐僧",
    "title": "我的绝美校花未婚妻",
    "cover": "860655",
    "categoryInfoV4Slave": "",
    "catName": "都市",
    "totalWords": "2453571",
    "pushName": "学阀:我的绝美校花未婚妻",
    "categoryInfoV4": "20000:小说:小说,20019:都市:都市,20026:异术超能:异能"
  },
    {
    "lpushname": "穿越来的秦天只想当一个好相公，让自己的家人过上好日子。",
    "cpushname": "我有娇妻美眷：大唐好相公",
    "finished": "0",
    "type": "0",
    "intro": "武德六年，大唐初定，百废待兴。\r\n太子稳坐东宫，李世民野心勃勃。\r\n武将定江山，文臣思治国。\r\n穿越来的秦天只",
    "id": "19911459",
    "cat3Info": "20000:小说:小说,20028:历史:历史,20029:架空历史:架空",
    "author": "古沐鱼",
    "title": "大唐好相公",
    "cover": "19911459",
    "categoryInfoV4Slave": "",
    "catName": "历史",
    "totalWords": "3755097",
    "pushName": "我有娇妻美眷：大唐好相公",
    "categoryInfoV4": "20000:小说:小说,20028:历史:历史,20029:架空历史:架空"
  },
    {
    "lpushname": "萧动尘重生了，渡劫失败的他重生成了一名身家百亿的富二代。",
    "cpushname": "都市之万界至尊",
    "finished": "0",
    "type": "0",
    "intro": "萧动尘重生了，渡劫失败的他重生成了一名身家百亿的富二代。\r\n从此以后，各种奇妙的遭遇频繁的发生在他身边。\r\n无",
    "id": "20280375",
    "cat3Info": "20000:小说:小说,20014:仙侠:仙侠,20017:现代修真:现修",
    "author": "之不道",
    "title": "都市之万界至尊",
    "cover": "20280375",
    "categoryInfoV4Slave": "",
    "catName": "仙侠",
    "totalWords": "2920612",
    "pushName": "都市之万界至尊",
    "categoryInfoV4": "20000:小说:小说,20014:仙侠:仙侠,20017:现代修真:现修"
  },
    {
    "lpushname": "有强悍天穹战甲，动辄屠神灭魔；有憾世时空要塞，泯灭圣灵妖皇。",
    "cpushname": "仙法对撞要塞炮:崩仙逆道",
    "finished": "0",
    "type": "0",
    "intro": "古老洪荒大陆，埋葬了多少秘密。曾经仙道的文明已经逝去，而如今是科技的横行时代！有强悍天穹战甲，动辄屠神灭魔；有",
    "id": "653495",
    "cat3Info": "20000:小说:小说,20001:玄幻:玄幻,20002:东方玄幻:东方玄幻",
    "author": "雨暮浮屠",
    "title": "崩仙逆道",
    "cover": "653495",
    "categoryInfoV4Slave": "",
    "catName": "玄幻",
    "totalWords": "11213893",
    "pushName": "仙法对撞要塞炮:崩仙逆道",
    "categoryInfoV4": "20000:小说:小说,20001:玄幻:玄幻,20002:东方玄幻:东方玄幻"
  }],
  "publicLoves": [
    {
    "lpushname": "为了寻找失踪的手下，吴邪寻到了无辜受牵连的少年黎簇。少年背后的伤疤成为吴邪解开沙漠古墓谜团的关键。威逼利诱之下，吴邪带着黎簇深入沙漠死亡禁地——古潼京。",
    "cpushname": "沙海（全二册）",
    "finished": "1",
    "type": "0",
    "intro": "为了寻找失踪的手下，吴邪寻到了无辜受牵连的少年黎簇。少年背后的伤疤成为吴邪解开沙漠古墓谜团的关键。威逼利诱之下",
    "id": "22529943",
    "cat3Info": ",,13107::",
    "author": "南派三叔",
    "title": "沙海（全二册）",
    "cover": "http:\/\/wfqqreader-1252317822.image.myqcloud.com\/cover\/943\/22529943\/b_22529943.jpg",
    "categoryInfoV4Slave": "10000:出版:出版,13100:小说:小说,13101:中国当代小说:当代",
    "catName": "小说",
    "totalWords": "262218",
    "pushName": "沙海（全二册）",
    "categoryInfoV4": "10000:出版:出版,13100:小说:小说,13107:侦探\/悬疑\/推理:悬疑"
  },
    {
    "lpushname": "她是他捧在心尖上的女人，他亦是她心中唯一的天，可生在皇家身不由己，心高气傲如她，亦要沦入这深宫之中，与诸多女人",
    "cpushname": "宫檐",
    "finished": "1",
    "type": "0",
    "intro": "她是他捧在心尖上的女人，他亦是她心中唯一的天，可生在皇家身不由己，心高气傲如她，亦要沦入这深宫之中，与诸多女人",
    "id": "22899740",
    "cat3Info": ",,14314::",
    "author": "阿琐",
    "title": "宫檐",
    "cover": "22899740",
    "categoryInfoV4Slave": "10000:出版:出版,14300:青春文学:青春,14307:大陆原创:大陆原创",
    "catName": "青春",
    "totalWords": "2348156",
    "pushName": "宫檐",
    "categoryInfoV4": "10000:出版:出版,14300:青春文学:青春,14314:古代言情:古言"
  },
    {
    "lpushname": "她一双纤手，剖尽世间冤魂！愿所有不公，终将沉冤昭雪，眼睛所见，云开月明。",
    "cpushname": "青玉案",
    "finished": "1",
    "type": "0",
    "intro": "她一双纤手，剖尽世间冤魂！愿所有不公，终将沉冤昭雪，眼睛所见，云开月明。",
    "id": "22983808",
    "cat3Info": ",,14314::",
    "author": "三嬷嬷",
    "title": "青玉案",
    "cover": "22983808",
    "categoryInfoV4Slave": "10000:出版:出版,14300:青春文学:青春,14311:悬疑\/惊悚:悬疑",
    "catName": "青春",
    "totalWords": "448018",
    "pushName": "青玉案",
    "categoryInfoV4": "10000:出版:出版,14300:青春文学:青春,14314:古代言情:古言"
  },
    {
    "lpushname": "他是外科医生中最冷酷的刀客，锋芒毕露。他曾声名狼藉，被封印在血色过往中，以为此生已然万劫不复。风波再起，他在命",
    "cpushname": "风再起时",
    "finished": "1",
    "type": "0",
    "intro": "他是外科医生中最冷酷的刀客，锋芒毕露。他曾声名狼藉，被封印在血色过往中，以为此生已然万劫不复。风波再起，他在命",
    "id": "23364834",
    "cat3Info": ",,14307::",
    "author": "穿行四季",
    "title": "风再起时",
    "cover": "http:\/\/wfqqreader-1252317822.image.myqcloud.com\/cover\/834\/23364834\/b_23364834.jpg",
    "categoryInfoV4Slave": "10000:出版:出版,14300:青春文学:青春,14302:爱情\/情感:情感",
    "catName": "青春",
    "totalWords": "194486",
    "pushName": "风再起时",
    "categoryInfoV4": "10000:出版:出版,14300:青春文学:青春,14307:大陆原创:大陆原创"
  },
    {
    "lpushname": "刺青，号称背在身上的神秘图腾。我就是一名传统刺青师，这些年来，我给客人们纹身遭遇诸多怪事，压抑着心里恐怖的秘密",
    "cpushname": "纹阴师",
    "finished": "0",
    "type": "0",
    "intro": "刺青，号称背在身上的神秘图腾。我就是一名传统刺青师，这些年来，我给客人们纹身遭遇诸多怪事，压抑着心里恐怖的秘密",
    "id": "927270",
    "cat3Info": ",,13108::",
    "author": "啃树",
    "title": "纹阴师",
    "cover": "927270",
    "categoryInfoV4Slave": "10000:出版:出版,13100:小说:小说,13107:侦探\/悬疑\/推理:悬疑",
    "catName": "小说",
    "totalWords": "2280072",
    "pushName": "纹阴师",
    "categoryInfoV4": "10000:出版:出版,13100:小说:小说,13108:惊悚\/恐怖:惊悚"
  }]
}
